os_cloud_config/__init__.py
os_cloud_config/_i18n.py
os_cloud_config/exception.py
os_cloud_config/flavors.py
os_cloud_config/glance.py
os_cloud_config/keystone.py
os_cloud_config/keystone_pki.py
os_cloud_config/neutron.py
os_cloud_config/nodes.py
os_cloud_config/cmd/__init__.py
os_cloud_config/cmd/generate_keystone_pki.py
os_cloud_config/cmd/init_keystone.py
os_cloud_config/cmd/init_keystone_heat_domain.py
os_cloud_config/cmd/register_nodes.py
os_cloud_config/cmd/setup_endpoints.py
os_cloud_config/cmd/setup_flavors.py
os_cloud_config/cmd/setup_neutron.py
os_cloud_config/cmd/upload_kernel_ramdisk.py
os_cloud_config/cmd/tests/__init__.py
os_cloud_config/cmd/tests/test_generate_keystone_pki.py
os_cloud_config/cmd/tests/test_init_keystone.py
os_cloud_config/cmd/tests/test_init_keystone_heat_domain.py
os_cloud_config/cmd/tests/test_register_nodes.py
os_cloud_config/cmd/tests/test_setup_endpoints.py
os_cloud_config/cmd/tests/test_setup_flavors.py
os_cloud_config/cmd/tests/test_setup_neutron.py
os_cloud_config/cmd/tests/test_upload_kernel_ramdisk.py
os_cloud_config/cmd/utils/__init__.py
os_cloud_config/cmd/utils/_clients.py
os_cloud_config/cmd/utils/environment.py
os_cloud_config/cmd/utils/tests/__init__.py
os_cloud_config/cmd/utils/tests/test_clients.py
os_cloud_config/cmd/utils/tests/test_environment.py
os_cloud_config/tests/__init__.py
os_cloud_config/tests/base.py
os_cloud_config/tests/test_flavors.py
os_cloud_config/tests/test_glance.py
os_cloud_config/tests/test_keystone.py
os_cloud_config/tests/test_keystone_pki.py
os_cloud_config/tests/test_neutron.py
os_cloud_config/tests/test_nodes.py
os_cloud_config/utils/__init__.py
os_cloud_config/utils/clients.py
os_cloud_config/utils/tests/__init__.py
os_cloud_config/utils/tests/test_clients.py
os_cloud_config-6.0.0.dist-info/DESCRIPTION.rst
os_cloud_config-6.0.0.dist-info/METADATA
os_cloud_config-6.0.0.dist-info/RECORD
os_cloud_config-6.0.0.dist-info/WHEEL
os_cloud_config-6.0.0.dist-info/entry_points.txt
os_cloud_config-6.0.0.dist-info/metadata.json
os_cloud_config-6.0.0.dist-info/pbr.json
os_cloud_config-6.0.0.dist-info/top_level.txt
