Metadata-Version: 2.0
Name: os-cloud-config
Version: 6.0.0
Summary: Configuration for OpenStack clouds.
Home-page: http://www.openstack.org/
Author: OpenStack
Author-email: openstack-dev@lists.openstack.org
License: UNKNOWN
Platform: UNKNOWN
Classifier: Environment :: OpenStack
Classifier: Intended Audience :: Information Technology
Classifier: Intended Audience :: System Administrators
Classifier: License :: OSI Approved :: Apache Software License
Classifier: Operating System :: POSIX :: Linux
Classifier: Programming Language :: Python
Classifier: Programming Language :: Python :: 2
Classifier: Programming Language :: Python :: 2.7
Classifier: Programming Language :: Python :: 3
Classifier: Programming Language :: Python :: 3.4
Requires-Dist: Babel (>=2.3.4)
Requires-Dist: oslo.config (!=3.18.0,>=3.14.0)
Requires-Dist: oslo.i18n (>=2.1.0)
Requires-Dist: pbr (>=1.8)
Requires-Dist: pyOpenSSL (>=0.14)
Requires-Dist: python-glanceclient (>=2.5.0)
Requires-Dist: python-ironicclient (>=1.9.0)
Requires-Dist: python-keystoneclient (>=3.8.0)
Requires-Dist: python-neutronclient (>=5.1.0)
Requires-Dist: python-novaclient (>=2.29.0,!=2.33.0)
Requires-Dist: six (>=1.9.0)
